{
  "name": "CANASTO GEMA O AQUA L75 22X34X11CM",
  "line": "accesorios",
  "category": "accesorio",
  "dimensions": {
    "width": 220,
    "depth": 340,
    "height": 110,
    "unit": "mm"
  },
  "material": "Acero de alta calidad AISI 304",
  "thickness": "0.6mm",
  "features": [
    "Acero de alta calidad AISI 304",
    "Alta durabilidad y resistencia",
    "Terminación satinada premium"
  ],
  "installationType": "bajo-mesada",
  "image": "/images/products/canasto-gema-o-aqua-l75-22x34x11cm-1.webp",
  "gallery": [],
  "sortOrder": 100,
  "featured": false,
  "available": true,
  "description": "Renová tu espacio con este producto de Masecor. La combinación perfecta entre estética y practicidad. Pensada para el uso intensivo, garantiza un mantenimiento sencillo y una vida útil prolongada. Especialmente diseñado para adaptarse a cualquier mesada y ofrecerte la mejor experiencia de uso.",
  "shortDescription": "La combinación perfecta entre estética y practicidad. Pensada para el uso intensivo, garantiza un mantenimiento sencillo y una vida útil prolongada."
}
